README.rst
setup.py
django_callable_perms/__init__.py
django_callable_perms/backends.py
django_callable_perms/models.py
django_callable_perms/template.py
django_callable_perms/tests.py
django_callable_perms/utils.py
django_callable_perms/views.py
django_callable_perms.egg-info/PKG-INFO
django_callable_perms.egg-info/SOURCES.txt
django_callable_perms.egg-info/dependency_links.txt
django_callable_perms.egg-info/requires.txt
django_callable_perms.egg-info/top_level.txt
django_callable_perms/management/__init__.py
django_callable_perms/management/commands/__init__.py
django_callable_perms/management/commands/sync_permissions.py
django_callable_perms/templatetags/__init__.py
django_callable_perms/templatetags/callable_perms_tags.py