Metadata-Version: 1.1
Name: django-callable-perms
Version: 0.1.2
Summary: Modular registry of permission handlers for Django
Home-page: https://github.com/ddanier/django_callable_perms
Author: David Danier
Author-email: david.danier@team23.de
License: UNKNOWN
Platform: UNKNOWN
Classifier: Development Status :: 4 - Beta
Classifier: Environment :: Web Environment
Classifier: Framework :: Django
Classifier: Intended Audience :: Developers
Classifier: License :: OSI Approved :: BSD License
Classifier: Operating System :: OS Independent
Classifier: Programming Language :: Python
Classifier: Topic :: Utilities
